sqreen/__about__.py
sqreen/__init__.py
sqreen/actions.py
sqreen/async_context.py
sqreen/binding_accessor.py
sqreen/ca.crt
sqreen/condition_evaluator.py
sqreen/config.py
sqreen/constants.py
sqreen/events.py
sqreen/exceptions.py
sqreen/http_client.py
sqreen/ip_radix.py
sqreen/list_filters.py
sqreen/log.py
sqreen/matcher.py
sqreen/metrics.py
sqreen/payload_creator.py
sqreen/performance_metrics.py
sqreen/remote_command.py
sqreen/remote_exception.py
sqreen/request_recorder.py
sqreen/rules.py
sqreen/runner.py
sqreen/runner_thread.py
sqreen/runtime_infos.py
sqreen/runtime_storage.py
sqreen/sanitizer.py
sqreen/session.py
sqreen/signature.py
sqreen/utils.py
sqreen/_vendors/__init__.py
sqreen/_vendors/distro.py
sqreen/_vendors/ipaddress.py
sqreen/_vendors/pyasn1/__init__.py
sqreen/_vendors/pyasn1/debug.py
sqreen/_vendors/pyasn1/error.py
sqreen/_vendors/pyasn1/codec/__init__.py
sqreen/_vendors/pyasn1/codec/ber/__init__.py
sqreen/_vendors/pyasn1/codec/ber/decoder.py
sqreen/_vendors/pyasn1/codec/ber/encoder.py
sqreen/_vendors/pyasn1/codec/ber/eoo.py
sqreen/_vendors/pyasn1/codec/cer/__init__.py
sqreen/_vendors/pyasn1/codec/cer/decoder.py
sqreen/_vendors/pyasn1/codec/cer/encoder.py
sqreen/_vendors/pyasn1/codec/der/__init__.py
sqreen/_vendors/pyasn1/codec/der/decoder.py
sqreen/_vendors/pyasn1/codec/der/encoder.py
sqreen/_vendors/pyasn1/codec/native/__init__.py
sqreen/_vendors/pyasn1/codec/native/decoder.py
sqreen/_vendors/pyasn1/codec/native/encoder.py
sqreen/_vendors/pyasn1/compat/__init__.py
sqreen/_vendors/pyasn1/compat/binary.py
sqreen/_vendors/pyasn1/compat/calling.py
sqreen/_vendors/pyasn1/compat/dateandtime.py
sqreen/_vendors/pyasn1/compat/integer.py
sqreen/_vendors/pyasn1/compat/octets.py
sqreen/_vendors/pyasn1/compat/string.py
sqreen/_vendors/pyasn1/type/__init__.py
sqreen/_vendors/pyasn1/type/base.py
sqreen/_vendors/pyasn1/type/char.py
sqreen/_vendors/pyasn1/type/constraint.py
sqreen/_vendors/pyasn1/type/error.py
sqreen/_vendors/pyasn1/type/namedtype.py
sqreen-1.18.2.dist-info/METADATA
sqreen-1.18.2.dist-info/WHEEL
sqreen-1.18.2.dist-info/entry_points.txt
sqreen-1.18.2.dist-info/top_level.txt
sqreen-1.18.2.dist-info/RECORD
