Metadata-Version: 2.1
Name: sqreen
Version: 1.18.2
Summary: Sqreen agent to protect Python applications.
Home-page: https://www.sqreen.com/
Author: Sqreen
Author-email: contact@sqreen.io
License: proprietary
Keywords: sqreen
Platform: UNKNOWN
Classifier: Development Status :: 5 - Production/Stable
Classifier: Intended Audience :: Developers
Classifier: License :: Other/Proprietary License
Classifier: Programming Language :: Python
Classifier: Programming Language :: Python :: 2
Classifier: Programming Language :: Python :: 2.7
Classifier: Programming Language :: Python :: 3
Classifier: Programming Language :: Python :: 3.4
Classifier: Programming Language :: Python :: 3.5
Classifier: Programming Language :: Python :: 3.6
Classifier: Programming Language :: Python :: 3.7
Classifier: Programming Language :: Python :: 3.8
Classifier: Topic :: Internet :: WWW/HTTP
Classifier: Topic :: Security
Requires-Dist: py-mini-racer (>=0.1.18)
Requires-Dist: sq-native (<1.0.0,>=0.5.1.0.1)
